Metadata-Version: 2.1
Name: moon-threejs
Version: 0.0.2
Summary: Threejs rendering of the moon
Home-page: UNKNOWN
Author: Ben Cannell <bean.can.design@gmail.com>
License: GPL-3.0
Platform: UNKNOWN
Classifier: Framework :: Dash
License-File: LICENSE
